wallpaper_changer
