Metadata-Version: 1.0
Name: wallpaper-finder
Version: 0.1.1
Summary: platform wallpaper changer
Home-page: https://github.com/JarbasAl/wallpaper_changer
Author: jarbasAI
Author-email: jarbasai@mailfence.com
License: Apache2.0
Platform: UNKNOWN
